README.md
setup.py
pulumiverse_doppler/__init__.py
pulumiverse_doppler/_inputs.py
pulumiverse_doppler/_utilities.py
pulumiverse_doppler/branch_config.py
pulumiverse_doppler/environment.py
pulumiverse_doppler/get_secrets.py
pulumiverse_doppler/get_user.py
pulumiverse_doppler/group.py
pulumiverse_doppler/group_member.py
pulumiverse_doppler/group_members.py
pulumiverse_doppler/outputs.py
pulumiverse_doppler/project.py
pulumiverse_doppler/project_role.py
pulumiverse_doppler/provider.py
pulumiverse_doppler/pulumi-plugin.json
pulumiverse_doppler/py.typed
pulumiverse_doppler/secret.py
pulumiverse_doppler/service_account.py
pulumiverse_doppler/service_account_token.py
pulumiverse_doppler/service_token.py
pulumiverse_doppler/webhook.py
pulumiverse_doppler.egg-info/PKG-INFO
pulumiverse_doppler.egg-info/SOURCES.txt
pulumiverse_doppler.egg-info/dependency_links.txt
pulumiverse_doppler.egg-info/not-zip-safe
pulumiverse_doppler.egg-info/requires.txt
pulumiverse_doppler.egg-info/top_level.txt
pulumiverse_doppler/config/__init__.py
pulumiverse_doppler/config/vars.py
pulumiverse_doppler/integration/__init__.py
pulumiverse_doppler/integration/aws_parameter_store.py
pulumiverse_doppler/integration/aws_secrets_manager.py
pulumiverse_doppler/integration/circleci.py
pulumiverse_doppler/integration/flyio.py
pulumiverse_doppler/integration/terraform_cloud.py
pulumiverse_doppler/projectmember/__init__.py
pulumiverse_doppler/projectmember/group.py
pulumiverse_doppler/projectmember/service_account.py
pulumiverse_doppler/secretssync/__init__.py
pulumiverse_doppler/secretssync/aws_parameter_store.py
pulumiverse_doppler/secretssync/aws_secrets_manager.py
pulumiverse_doppler/secretssync/circleci.py
pulumiverse_doppler/secretssync/flyio.py
pulumiverse_doppler/secretssync/github_actions.py
pulumiverse_doppler/secretssync/terraform_cloud.py