Metadata-Version: 2.1
Name: pulumiverse-doppler
Version: 0.9.0
Summary: A Pulumi package for creating and managing doppler cloud resources.
Home-page: https://www.pulumi.com
License: Apache-2.0
Project-URL: Repository, https://github.com/pulumiverse/pulumi-doppler
Keywords: pulumi doppler category/cloud
Platform: UNKNOWN
Requires-Python: >=3.8
